fermata/__init__.py
fermata/__main__.py
fermata/application.py
fermata/exception.py
fermata/future.py
fermata/jwt.py
fermata/loader.py
fermata/request.py
fermata/response.py
fermata/trie.py
fermata/ext/apm/__init__.py
fermata/ext/apm/util.py
fermata/openapi/__init__.py
fermata/openapi/authorizer.py
fermata/openapi/jsonschema.py
fermata/openapi/operator.py
fermata/openapi/router.py
fermata/openapi/specification.py
fermata/openapi/validator.py
fermata-0.0.4.dist-info/METADATA
fermata-0.0.4.dist-info/WHEEL
fermata-0.0.4.dist-info/top_level.txt
fermata-0.0.4.dist-info/RECORD
