Metadata-Version: 2.1
Name: fermata
Version: 0.0.4
Summary: A WSGI Server Implementation of OpenAPI 3.0 in Python3.
Home-page: https://fenda.io/ff/fermata
Author: rejown
Author-email: rejown@gmail.com
License: UNKNOWN
Platform: UNKNOWN
Requires-Python: >=3.6
Requires-Dist: jsonschema
